NseUtility/Nseutils.py
NseUtility/__init__.py
nseutility-0.2.3.dist-info/METADATA
nseutility-0.2.3.dist-info/WHEEL
nseutility-0.2.3.dist-info/top_level.txt
nseutility-0.2.3.dist-info/RECORD
