Metadata-Version: 2.4
Name: NseUtility
Version: 0.2.3
Summary: A utility to fetch NSE India data
Author: Prasad
Requires-Python: >=3.8
Requires-Dist: pandas
Requires-Dist: requests
Requires-Dist: numpy
Requires-Dist: gspread
Requires-Dist: oauth2client
Requires-Dist: google-auth
Requires-Dist: schedule
Requires-Dist: pytz
Requires-Dist: beautifulsoup4
Dynamic: author
Dynamic: requires-dist
Dynamic: requires-python
Dynamic: summary
